PyLocalizer/EntryFormatting.py
PyLocalizer/WebLocalization.py
PyLocalizer/__init__.py
PyLocalizer/internal/JSONLocalization.py
PyLocalizer/internal/RawLocalization.py
PyLocalizer/internal/__init__.py
pylocalizer-0.0.4.dist-info/LICENSE
pylocalizer-0.0.4.dist-info/METADATA
pylocalizer-0.0.4.dist-info/WHEEL
pylocalizer-0.0.4.dist-info/top_level.txt
pylocalizer-0.0.4.dist-info/RECORD
